satellite/__init__.py
satellite/data/ADM.duckdb
satellite/data/gpkgs/ARG.zip
satellite/data/gpkgs/BRA/BRA_1.zip
satellite/data/gpkgs/BRA/BRA_10.zip
satellite/data/gpkgs/BRA/BRA_11.zip
satellite/data/gpkgs/BRA/BRA_2.zip
satellite/data/gpkgs/BRA/BRA_3.zip
satellite/data/gpkgs/BRA/BRA_4.zip
satellite/data/gpkgs/BRA/BRA_5.zip
satellite/data/gpkgs/BRA/BRA_6.zip
satellite/data/gpkgs/BRA/BRA_7.zip
satellite/data/gpkgs/BRA/BRA_8.zip
satellite/data/gpkgs/BRA/BRA_9.zip
satellite/data/gpkgs/README.md
satellite/extensions/cope.py
satellite/geo/constants.py
satellite/geo/functional.py
satellite/geo/models.py
satellite/models.py
satellite/request.py
satellite_weather_downloader-1.11.3.dist-info/LICENSE
satellite_weather_downloader-1.11.3.dist-info/METADATA
satellite_weather_downloader-1.11.3.dist-info/WHEEL
satellite_weather_downloader-1.11.3.dist-info/RECORD
