Metadata-Version: 2.3
Name: satellite-weather-downloader
Version: 1.11.3
Summary: The modules available in this package are designed to capture and proccess satellite data from Copernicus
License: GNU GPL v3.0
Author: Luã Bida Vacaro
Author-email: luabidaa@gmail.com
Maintainer: Luã Bida Vacaro
Maintainer-email: luabidaa@gmail.com
Requires-Python: >=3.10,<4
Classifier: Development Status :: 3 - Alpha
Classifier: Intended Audience :: Developers
Classifier: License :: OSI Approved :: GNU General Public License v3 or later (GPLv3+)
Classifier: License :: Other/Proprietary License
Classifier: Operating System :: OS Independent
Classifier: Programming Language :: Python :: 3
Classifier: Programming Language :: Python :: 3.10
Classifier: Programming Language :: Python :: 3.11
Classifier: Programming Language :: Python :: 3.12
Classifier: Programming Language :: Python :: 3.13
Classifier: Topic :: Software Development :: Libraries :: Python Modules
Requires-Dist: cdsapi (>=0.7.3)
Requires-Dist: duckdb (>=1.1.2,<2.0.0)
Requires-Dist: duckdb-engine (>=0.13.2,<0.14.0)
Requires-Dist: epiweeks (>=2.3.0,<3.0.0)
Requires-Dist: geopandas (>=1.0.1)
Requires-Dist: h5netcdf (>=1.4.0,<2.0.0)
Requires-Dist: loguru (>=0.6.0,<0.7.0)
Requires-Dist: matplotlib (>=3.6.3,<4.0.0)
Requires-Dist: netCDF4 (>=1.6.1,<2.0.0)
Requires-Dist: numpy (<2.0.0)
Requires-Dist: pandas (<2)
Requires-Dist: pydantic (>=2.9.2,<3.0.0)
Requires-Dist: python-dotenv (>=0.21.0,<0.22.0)
Requires-Dist: requests (>=2.28.2,<3.0.0)
Requires-Dist: rioxarray (>=0.17.0,<0.18.0)
Requires-Dist: shapely (>=2.0.3)
Requires-Dist: tqdm (>=4.64.1,<5.0.0)
Requires-Dist: typing-extensions (>=4.12.2,<5.0.0)
Requires-Dist: xagg (>=0.3.2.4,<0.4.0.0)
Requires-Dist: xarray (<2024.10)
Project-URL: Homepage, https://github.com/osl-incubator/satellite-weather-downloader
Project-URL: Repository, https://github.com/osl-incubator/satellite-weather-downloader
